azureml/__init__.py
azureml/_cli_common/__init__.py
azureml/_cli_common/all_parameters.py
azureml/_cli_common/cli_exception_handler.py
azureml/_cli_common/cli_workspace.py
azureml/_cli_common/commands_utility.py
azureml/_cli_common/constants.py
azureml/_cli_common/ml_cli_error.py
azureml/_cli_common/transformers.py
azureml_cli_common-1.60.0.dist-info/licenses/LICENSE.txt
azureml_cli_common-1.60.0.dist-info/METADATA
azureml_cli_common-1.60.0.dist-info/WHEEL
azureml_cli_common-1.60.0.dist-info/namespace_packages.txt
azureml_cli_common-1.60.0.dist-info/top_level.txt
azureml_cli_common-1.60.0.dist-info/RECORD
