Metadata-Version: 2.4
Name: azureml-cli-common
Version: 1.60.0
Summary: (v1) Manage Azure Machine Learning resources.    It is recommended to use the 2.0 extension - see aka.ms/azml2
Home-page: https://docs.microsoft.com/python/api/overview/azure/ml/?view=azure-ml-py
Author: Microsoft Corp
License: https://aka.ms/azureml-sdk-license
Classifier: Development Status :: 3 - Alpha
Classifier: Intended Audience :: Developers
Classifier: Intended Audience :: System Administrators
Classifier: Programming Language :: Python :: 3
Classifier: Programming Language :: Python :: 3.8
Classifier: Programming Language :: Python :: 3.9
Classifier: Programming Language :: Python :: 3.10
Classifier: Programming Language :: Python :: 3.11
Requires-Python: >=3.8,<4.0
License-File: LICENSE.txt
Requires-Dist: azureml-core~=1.60.0
Requires-Dist: azureml-pipeline-core~=1.60.0
Requires-Dist: azureml-train-core~=1.60.0; python_version >= "3.5"
Dynamic: author
Dynamic: classifier
Dynamic: description
Dynamic: description-content-type
Dynamic: home-page
Dynamic: license
Dynamic: license-file
Dynamic: requires-dist
Dynamic: requires-python
Dynamic: summary
